{
  "id": "archeidos-automations",
  "title": "Archeidos' 5e Automations",
  "version": "0.1.0",
  "compatibility": {
    "minimum": "12",
    "verified": "12",
    "maximum": "12"
  },
  "relationships": {
    "requires": [
      {
        "id": "midi-qol",
        "type": "module",
        "compatibility": {}
      },
      {
        "id": "dae",
        "type": "module",
        "compatibility": {}
      }
    ],
    "systems": [
      {
        "id": "dnd5e",
        "type": "system",
        "compatibility": {}
      }
    ]
  },
  "authors": [
    {
      "name": "Archeidos",
      "discord": "archeidos",
      "flags": {}
    }
  ]
}
